{
  "nodes": {
    "SitePage /dev-404-page/": {
      "path": "/dev-404-page/",
      "id": "SitePage /dev-404-page/",
      "parent": "SOURCE",
      "children": [],
      "internal": {
        "type": "SitePage",
        "contentDigest": "f91d29e10ba680b413138cf9ed86e655",
        "owner": "internal-data-bridge"
      }
    },
    "Plugin dev-404-page": {
      "resolve": "/home/saraband/Desktop/DEV/my-website NEXT/node_modules/gatsby/dist/internal-plugins/dev-404-page",
      "id": "Plugin dev-404-page",
      "name": "dev-404-page",
      "version": "1.0.0",
      "pluginOptions": {
        "plugins": []
      },
      "nodeAPIs": [
        "createPagesStatefully"
      ],
      "browserAPIs": [],
      "ssrAPIs": [],
      "pluginFilepath": "/home/saraband/Desktop/DEV/my-website NEXT/node_modules/gatsby/dist/internal-plugins/dev-404-page",
      "packageJson": {
        "name": "dev-404-page",
        "description": "Internal plugin to add a 404 page in development with helpful information",
        "version": "1.0.0",
        "main": "index.js",
        "author": "Kyle Mathews <mathews.kyle@gmail.com>",
        "license": "MIT",
        "dependencies": [],
        "devDependencies": [],
        "peerDependencies": [],
        "optionalDependecies": [],
        "bundledDependecies": []
      },
      "parent": "SOURCE",
      "children": [],
      "internal": {
        "contentDigest": "3d92d36ac71a630ec844ba80277b53e1",
        "type": "SitePlugin",
        "owner": "internal-data-bridge"
      }
    },
    "Plugin component-page-creator": {
      "resolve": "/home/saraband/Desktop/DEV/my-website NEXT/node_modules/gatsby/dist/internal-plugins/component-page-creator",
      "id": "Plugin component-page-creator",
      "name": "component-page-creator",
      "version": "1.0.0",
      "pluginOptions": {
        "plugins": []
      },
      "nodeAPIs": [
        "createPagesStatefully"
      ],
      "browserAPIs": [],
      "ssrAPIs": [],
      "pluginFilepath": "/home/saraband/Desktop/DEV/my-website NEXT/node_modules/gatsby/dist/internal-plugins/component-page-creator",
      "packageJson": {
        "name": "component-page-creator",
        "description": "An internal Gatsby plugin that creates pages from component files in src/pages",
        "version": "1.0.0",
        "main": "index.js",
        "keywords": [
          "gatsby",
          "gatsby-plugin"
        ],
        "author": "Kyle Mathews <mathews.kyle@gmail.com>",
        "license": "MIT",
        "dependencies": [],
        "devDependencies": [],
        "peerDependencies": [],
        "optionalDependecies": [],
        "bundledDependecies": []
      },
      "parent": "SOURCE",
      "children": [],
      "internal": {
        "contentDigest": "502f162bee52aa4cedee3ccdc31c4fde",
        "type": "SitePlugin",
        "owner": "internal-data-bridge"
      }
    },
    "Plugin component-layout-creator": {
      "resolve": "/home/saraband/Desktop/DEV/my-website NEXT/node_modules/gatsby/dist/internal-plugins/component-layout-creator",
      "id": "Plugin component-layout-creator",
      "name": "component-layout-creator",
      "version": "1.0.0",
      "pluginOptions": {
        "plugins": []
      },
      "nodeAPIs": [
        "createLayouts"
      ],
      "browserAPIs": [],
      "ssrAPIs": [],
      "pluginFilepath": "/home/saraband/Desktop/DEV/my-website NEXT/node_modules/gatsby/dist/internal-plugins/component-layout-creator",
      "packageJson": {
        "name": "component-layout-creator",
        "description": "An internal Gatsby plugin that creates pages from component files in src/layouts",
        "version": "1.0.0",
        "main": "index.js",
        "keywords": [
          "gatsby",
          "gatsby-plugin"
        ],
        "author": "Kyle Mathews <mathews.kyle@gmail.com>",
        "license": "MIT",
        "dependencies": [],
        "devDependencies": [],
        "peerDependencies": [],
        "optionalDependecies": [],
        "bundledDependecies": []
      },
      "parent": "SOURCE",
      "children": [],
      "internal": {
        "contentDigest": "aa49bb231b054ed7b7323508b09aa580",
        "type": "SitePlugin",
        "owner": "internal-data-bridge"
      }
    },
    "Plugin internal-data-bridge": {
      "resolve": "/home/saraband/Desktop/DEV/my-website NEXT/node_modules/gatsby/dist/internal-plugins/internal-data-bridge",
      "id": "Plugin internal-data-bridge",
      "name": "internal-data-bridge",
      "version": "1.0.0",
      "pluginOptions": {
        "plugins": []
      },
      "nodeAPIs": [
        "sourceNodes",
        "onCreatePage"
      ],
      "browserAPIs": [],
      "ssrAPIs": [],
      "pluginFilepath": "/home/saraband/Desktop/DEV/my-website NEXT/node_modules/gatsby/dist/internal-plugins/internal-data-bridge",
      "packageJson": {
        "name": "internal-data-bridge",
        "description": "An internal Gatsby plugin which creates data nodes from internal data",
        "version": "1.0.0",
        "main": "index.js",
        "author": "Kyle Mathews <mathews.kyle@gmail.com>",
        "license": "MIT",
        "dependencies": [],
        "devDependencies": [],
        "peerDependencies": [],
        "optionalDependecies": [],
        "bundledDependecies": []
      },
      "parent": "SOURCE",
      "children": [],
      "internal": {
        "contentDigest": "5cf1bc142d018a1758c2e1c7c1bd0f14",
        "type": "SitePlugin",
        "owner": "internal-data-bridge"
      }
    },
    "Plugin prod-404": {
      "resolve": "/home/saraband/Desktop/DEV/my-website NEXT/node_modules/gatsby/dist/internal-plugins/prod-404",
      "id": "Plugin prod-404",
      "name": "prod-404",
      "version": "1.0.0",
      "pluginOptions": {
        "plugins": []
      },
      "nodeAPIs": [
        "onCreatePage"
      ],
      "browserAPIs": [],
      "ssrAPIs": [],
      "pluginFilepath": "/home/saraband/Desktop/DEV/my-website NEXT/node_modules/gatsby/dist/internal-plugins/prod-404",
      "packageJson": {
        "name": "prod-404",
        "description": "Internal plugin to detect various flavors of 404 pages and ensure there's a 404.html path created as well to ensure compatability with static hosts",
        "version": "1.0.0",
        "main": "index.js",
        "author": "Kyle Mathews <mathews.kyle@gmail.com>",
        "license": "MIT",
        "dependencies": [],
        "devDependencies": [],
        "peerDependencies": [],
        "optionalDependecies": [],
        "bundledDependecies": []
      },
      "parent": "SOURCE",
      "children": [],
      "internal": {
        "contentDigest": "c08a6e4f00af82269e924a3aa47b038f",
        "type": "SitePlugin",
        "owner": "internal-data-bridge"
      }
    },
    "Plugin query-runner": {
      "resolve": "/home/saraband/Desktop/DEV/my-website NEXT/node_modules/gatsby/dist/internal-plugins/query-runner",
      "id": "Plugin query-runner",
      "name": "query-runner",
      "version": "1.0.0",
      "pluginOptions": {
        "plugins": []
      },
      "nodeAPIs": [
        "onCreatePage",
        "onCreateLayout"
      ],
      "browserAPIs": [],
      "ssrAPIs": [],
      "pluginFilepath": "/home/saraband/Desktop/DEV/my-website NEXT/node_modules/gatsby/dist/internal-plugins/query-runner",
      "packageJson": {
        "name": "query-runner",
        "description": "Internal plugin for running queries",
        "version": "1.0.0",
        "main": "index.js",
        "author": "",
        "license": "MIT",
        "dependencies": [],
        "devDependencies": [],
        "peerDependencies": [],
        "optionalDependecies": [],
        "bundledDependecies": []
      },
      "parent": "SOURCE",
      "children": [],
      "internal": {
        "contentDigest": "fda9348ec8bbb096b26c524c2ef88e05",
        "type": "SitePlugin",
        "owner": "internal-data-bridge"
      }
    },
    "Plugin gatsby-plugin-react-helmet": {
      "resolve": "/home/saraband/Desktop/DEV/my-website NEXT/node_modules/gatsby-plugin-react-helmet",
      "id": "Plugin gatsby-plugin-react-helmet",
      "name": "gatsby-plugin-react-helmet",
      "version": "2.0.11",
      "pluginOptions": {
        "plugins": []
      },
      "nodeAPIs": [],
      "browserAPIs": [],
      "ssrAPIs": [
        "onRenderBody"
      ],
      "pluginFilepath": "/home/saraband/Desktop/DEV/my-website NEXT/node_modules/gatsby-plugin-react-helmet",
      "packageJson": {
        "name": "gatsby-plugin-react-helmet",
        "description": "Manage document head data with react-helmet. Provides drop-in server rendering support for Gatsby.",
        "version": "2.0.11",
        "main": "index.js",
        "keywords": [
          "gatsby",
          "gatsby-plugin",
          "favicon",
          "react-helmet",
          "seo",
          "document",
          "head",
          "title",
          "meta",
          "link",
          "script",
          "base",
          "noscript",
          "style"
        ],
        "author": "Kyle Mathews <matthews.kyle@gmail.com>",
        "license": "MIT",
        "dependencies": [
          {
            "name": "babel-runtime",
            "version": "^6.26.0"
          }
        ],
        "devDependencies": [
          {
            "name": "babel-cli",
            "version": "^6.26.0"
          },
          {
            "name": "cross-env",
            "version": "^5.0.5"
          }
        ],
        "peerDependencies": [
          {
            "name": "gatsby",
            "version": "^1.0.0"
          },
          {
            "name": "react-helmet",
            "version": ">=5.1.3"
          }
        ],
        "optionalDependecies": [],
        "bundledDependecies": []
      },
      "parent": "SOURCE",
      "children": [],
      "internal": {
        "contentDigest": "db81ee4d0ff9aaab1ca492e8a763ac39",
        "type": "SitePlugin",
        "owner": "internal-data-bridge"
      }
    },
    "Plugin gatsby-plugin-sass": {
      "resolve": "/home/saraband/Desktop/DEV/my-website NEXT/node_modules/gatsby-plugin-sass",
      "id": "Plugin gatsby-plugin-sass",
      "name": "gatsby-plugin-sass",
      "version": "1.0.26",
      "pluginOptions": {
        "plugins": []
      },
      "nodeAPIs": [
        "modifyWebpackConfig"
      ],
      "browserAPIs": [],
      "ssrAPIs": [],
      "pluginFilepath": "/home/saraband/Desktop/DEV/my-website NEXT/node_modules/gatsby-plugin-sass",
      "packageJson": {
        "name": "gatsby-plugin-sass",
        "description": "Gatsby plugin to handle scss/sass files",
        "version": "1.0.26",
        "main": "index.js",
        "keywords": [
          "gatsby",
          "gatsby-plugin",
          "sass",
          "scss"
        ],
        "author": "Daniel Farrell <daniel@mobelux.com>",
        "license": "MIT",
        "dependencies": [
          {
            "name": "babel-runtime",
            "version": "^6.26.0"
          },
          {
            "name": "gatsby-1-config-css-modules",
            "version": "^1.0.11"
          },
          {
            "name": "gatsby-1-config-extract-plugin",
            "version": "^1.0.3"
          },
          {
            "name": "node-sass",
            "version": "^4.5.2"
          },
          {
            "name": "sass-loader",
            "version": "^4.1.1"
          },
          {
            "name": "webpack",
            "version": "^1.13.3"
          }
        ],
        "devDependencies": [
          {
            "name": "babel-cli",
            "version": "^6.26.0"
          },
          {
            "name": "cross-env",
            "version": "^5.0.5"
          }
        ],
        "peerDependencies": [
          {
            "name": "gatsby",
            "version": "^1.0.0"
          }
        ],
        "optionalDependecies": [],
        "bundledDependecies": []
      },
      "parent": "SOURCE",
      "children": [],
      "internal": {
        "contentDigest": "112c69a4ce7d0ac2b25714a42e9df6cb",
        "type": "SitePlugin",
        "owner": "internal-data-bridge"
      }
    },
    "Plugin @jacobmischka/gatsby-plugin-react-svg": {
      "resolve": "/home/saraband/Desktop/DEV/my-website NEXT/node_modules/@jacobmischka/gatsby-plugin-react-svg",
      "id": "Plugin @jacobmischka/gatsby-plugin-react-svg",
      "name": "@jacobmischka/gatsby-plugin-react-svg",
      "version": "1.1.0",
      "pluginOptions": {
        "plugins": []
      },
      "nodeAPIs": [
        "modifyWebpackConfig"
      ],
      "browserAPIs": [],
      "ssrAPIs": [],
      "pluginFilepath": "/home/saraband/Desktop/DEV/my-website NEXT/node_modules/@jacobmischka/gatsby-plugin-react-svg",
      "packageJson": {
        "name": "@jacobmischka/gatsby-plugin-react-svg",
        "description": "Adds svg-react-loader to gatsby webpack config.",
        "version": "1.1.0",
        "main": "gatsby-node.js",
        "keywords": [
          "gatsby",
          "svg",
          "react"
        ],
        "author": "Jacob Mischka <jacob@mischka.me>",
        "license": "MIT",
        "dependencies": [
          {
            "name": "svg-react-loader",
            "version": "^0.4.4"
          }
        ],
        "devDependencies": [],
        "peerDependencies": [],
        "optionalDependecies": [],
        "bundledDependecies": []
      },
      "parent": "SOURCE",
      "children": [],
      "internal": {
        "contentDigest": "a58491f3861978687464ef6834cbd940",
        "type": "SitePlugin",
        "owner": "internal-data-bridge"
      }
    },
    "Plugin default-site-plugin": {
      "resolve": "/home/saraband/Desktop/DEV/my-website NEXT",
      "id": "Plugin default-site-plugin",
      "name": "default-site-plugin",
      "version": "9854b1439a21a9bccb14fc9250169f8d",
      "pluginOptions": {
        "plugins": []
      },
      "nodeAPIs": [
        "modifyBabelrc"
      ],
      "browserAPIs": [
        "replaceRouterComponent"
      ],
      "ssrAPIs": [
        "replaceRenderer"
      ],
      "pluginFilepath": "/home/saraband/Desktop/DEV/my-website NEXT",
      "packageJson": {
        "name": "gatsby-starter-default",
        "description": "Gatsby default starter",
        "version": "1.0.0",
        "keywords": [
          "gatsby"
        ],
        "author": "Kyle Mathews <mathews.kyle@gmail.com>",
        "license": "MIT",
        "dependencies": [
          {
            "name": "@jacobmischka/gatsby-plugin-react-svg",
            "version": "^1.1.0"
          },
          {
            "name": "babel-plugin-transform-regenerator",
            "version": "^6.26.0"
          },
          {
            "name": "gatsby",
            "version": "^1.9.247"
          },
          {
            "name": "gatsby-link",
            "version": "^1.6.40"
          },
          {
            "name": "gatsby-plugin-react-helmet",
            "version": "^2.0.10"
          },
          {
            "name": "gatsby-plugin-sass",
            "version": "^1.0.26"
          },
          {
            "name": "react-helmet",
            "version": "^5.2.0"
          },
          {
            "name": "react-redux",
            "version": "^5.0.7"
          },
          {
            "name": "redux",
            "version": "^4.0.0"
          },
          {
            "name": "redux-thunk",
            "version": "^2.3.0"
          }
        ],
        "devDependencies": [
          {
            "name": "prettier",
            "version": "^1.12.0"
          }
        ],
        "peerDependencies": [],
        "optionalDependecies": [],
        "bundledDependecies": []
      },
      "parent": "SOURCE",
      "children": [],
      "internal": {
        "contentDigest": "1d76d3ca4a961f06b38349c33bd7758a",
        "type": "SitePlugin",
        "owner": "internal-data-bridge"
      }
    },
    "Site": {
      "siteMetadata": {
        "title": "Yassine Hermellin"
      },
      "pathPrefix": "",
      "polyfill": true,
      "buildTime": "2018-05-30T10:05:08.698Z",
      "id": "Site",
      "parent": "SOURCE",
      "children": [],
      "internal": {
        "contentDigest": "2aa0b6e5b582b589dfbd549200b630b8",
        "type": "Site",
        "owner": "internal-data-bridge"
      }
    },
    "SitePage /": {
      "layout": null,
      "jsonName": "index.json",
      "internalComponentName": "ComponentIndex",
      "path": "/",
      "component": "/home/saraband/Desktop/DEV/my-website NEXT/src/pages/index.js",
      "componentChunkName": "component---src-pages-index-js",
      "context": {},
      "pluginCreator___NODE": "Plugin component-page-creator",
      "pluginCreatorId": "Plugin component-page-creator",
      "componentPath": "/home/saraband/Desktop/DEV/my-website NEXT/src/pages/index.js",
      "id": "SitePage /",
      "parent": "SOURCE",
      "children": [],
      "internal": {
        "type": "SitePage",
        "contentDigest": "0a470ac934843629cdd94ba4fa2afa7d",
        "description": "Plugin component-page-creator",
        "owner": "internal-data-bridge"
      }
    }
  },
  "status": {
    "plugins": {},
    "PLUGINS_HASH": "c2f679ac8fb6bbd19401e4b1988b3e00"
  },
  "componentDataDependencies": {
    "nodes": {},
    "connections": {}
  }
}